twixt/VERSION
twixt/__init__.py
twixt/composed_step.py
twixt/logging.py
twixt/py.typed
twixt/timeline.py
twixt/track.py
twixt/types.py
twixt/version.py
twixt-1.0.0a8.dist-info/LICENSE
twixt-1.0.0a8.dist-info/METADATA
twixt-1.0.0a8.dist-info/WHEEL
twixt-1.0.0a8.dist-info/top_level.txt
twixt-1.0.0a8.dist-info/RECORD
