Metadata-Version: 2.1
Name: twixt
Version: 1.0.0a8
Summary: Betwixt two values
Home-page: https://github.com/cariad/twixt
Author: Cariad Eccleston
Author-email: cariad@cariad.earth
License: MIT
Classifier: Development Status :: 3 - Alpha
Classifier: License :: OSI Approved :: MIT License
Classifier: Natural Language :: English
Classifier: Operating System :: OS Independent
Classifier: Programming Language :: Python :: 3 :: Only
Classifier: Programming Language :: Python :: 3.11
Classifier: Typing :: Typed
Requires-Python: >=3.11
License-File: LICENSE
Requires-Dist: bendy ==1.0.0a10
Provides-Extra: draw
Requires-Dist: bendy[draw] ==1.0.0a10 ; extra == 'draw'
